Mithra_SST/__init__.py
mr_dako_sst-0.1.dist-info/METADATA
mr_dako_sst-0.1.dist-info/WHEEL
mr_dako_sst-0.1.dist-info/top_level.txt
mr_dako_sst-0.1.dist-info/RECORD
