Metadata-Version: 2.4
Name: mr_dako_SST
Version: 0.1
Summary: This is speech to text application created by Krishna Prcleaasad
Author: Krishna Prasad 
Author-email: kp8808711@gmail.com
Dynamic: author
Dynamic: author-email
Dynamic: summary
